transformer_keras/__init__.py
transformer_keras/layers.py
transformer_keras/model.py
transformer_keras-0.1.dist-info/METADATA
transformer_keras-0.1.dist-info/RECORD
transformer_keras-0.1.dist-info/WHEEL
transformer_keras-0.1.dist-info/top_level.txt
