Metadata-Version: 2.1
Name: transformer-keras
Version: 0.1
Summary: transformer_keras encoder implemented with keras
Home-page: UNKNOWN
Author: MrWaterZhou
Author-email: zhou_wuxialang@qq.com
License: UNKNOWN
Platform: UNKNOWN
Classifier: Programming Language :: Python :: 3
Classifier: License :: OSI Approved :: MIT License
Classifier: Operating System :: OS Independent
